lattica_deployer/__init__.py
lattica_deployer/common.py
lattica_deployer/examples/__init__.py
lattica_deployer/examples/deployment_demo.py
lattica_deployer/lattica_deploy.py
lattica_deployer-0.5.1.dist-info/METADATA
lattica_deployer-0.5.1.dist-info/WHEEL
lattica_deployer-0.5.1.dist-info/RECORD
